libname/__init__.py
libname/hello.py
hellopkg_shweta-0.0.1.dist-info/METADATA
hellopkg_shweta-0.0.1.dist-info/WHEEL
hellopkg_shweta-0.0.1.dist-info/top_level.txt
hellopkg_shweta-0.0.1.dist-info/RECORD
